CHANGES.txt
LICENSE.txt
MANIFEST.in
README.txt
setup.py
js/__init__.py
js.forkit.egg-info/PKG-INFO
js.forkit.egg-info/SOURCES.txt
js.forkit.egg-info/dependency_links.txt
js.forkit.egg-info/entry_points.txt
js.forkit.egg-info/namespace_packages.txt
js.forkit.egg-info/not-zip-safe
js.forkit.egg-info/requires.txt
js.forkit.egg-info/top_level.txt
js/forkit/__init__.py
js/forkit/test_forkit.js.txt
js/forkit/resources/css/forkit.css
js/forkit/resources/css/forkit.min.css
js/forkit/resources/js/forkit.js
js/forkit/resources/js/forkit.min.js