Metadata-Version: 1.0
Name: js.forkit
Version: 0.2
Summary: Fanstatic packaging of forkit.js
Home-page: https://github.com/disko/js.forkit/
Author: Andreas Kaiser
Author-email: disko@binary-punks.com
License: BSD
Platform: UNKNOWN
